lrtm_s5ptn/__init__.py
lrtm_s5ptn/tropomi/__init__.py
lrtm_s5ptn/tropomi/no2/__init__.py
lrtm_s5ptn/tropomi/no2/converter.py
lrtm_s5ptn/tropomi/no2/cp_completion.py
lrtm_s5ptn/tropomi/no2/imputation.py
lrtm_s5ptn/tropomi/no2/kriging.py
lrtm_s5ptn/tropomi/no2/utils.py
lrtm_s5ptn-1.41.dist-info/LICENSE
lrtm_s5ptn-1.41.dist-info/METADATA
lrtm_s5ptn-1.41.dist-info/WHEEL
lrtm_s5ptn-1.41.dist-info/top_level.txt
lrtm_s5ptn-1.41.dist-info/RECORD
