Metadata-Version: 2.1
Name: lrtm-s5ptn
Version: 1.41
Summary: Low Rank Tensor Modeling of Sentinel 5P Tropospheric NO2
Author: Ryan Solgi
Author-email: ryan.solgi@gmail.com
Maintainer: Ryan Solgi
Keywords: lrtm-s5ptn
Classifier: Programming Language :: Python :: 3
Classifier: License :: OSI Approved :: MIT License
Classifier: Operating System :: OS Independent
Classifier: Topic :: Software Development :: Libraries :: Python Modules
License-File: LICENSE
Requires-Dist: numpy
Requires-Dist: datetime
Requires-Dist: netCDF4
Requires-Dist: pandas
Requires-Dist: geopandas
Requires-Dist: rasterio
Requires-Dist: tensorlearn
